<?xml version="1.0" encoding="UTF-8"?>
<issues format="6" by="lint 7.4.2" type="baseline" client="gradle" dependencies="false" name="AGP (7.4.2)" variant="all" version="7.4.2">

    <issue
        id="UnusedResources"
        message="The resource `R.drawable.cap_btn_background_dark` appears to be unused"
        errorLine1="&lt;ripple xmlns:android=&quot;http://schemas.android.com/apk/res/android&quot;"
        errorLine2="^">
        <location
            file="src/main/res/drawable/cap_btn_background_dark.xml"
            line="2"
            column="1"/>
    </issue>

    <issue
        id="UnusedResources"
        message="The resource `R.drawable.cap_btn_background_light` appears to be unused"
        errorLine1="&lt;ripple xmlns:android=&quot;http://schemas.android.com/apk/res/android&quot;"
        errorLine2="^">
        <location
            file="src/main/res/drawable/cap_btn_background_light.xml"
            line="2"
            column="1"/>
    </issue>

    <issue
        id="UnusedResources"
        message="The resource `R.drawable.cap_logo_dark` appears to be unused"
        errorLine1="&lt;vector xmlns:android=&quot;http://schemas.android.com/apk/res/android&quot;"
        errorLine2="^">
        <location
            file="src/main/res/drawable/cap_logo_dark.xml"
            line="1"
            column="1"/>
    </issue>

    <issue
        id="UnusedResources"
        message="The resource `R.drawable.cap_logo_light` appears to be unused"
        errorLine1="&lt;vector xmlns:android=&quot;http://schemas.android.com/apk/res/android&quot;"
        errorLine2="^">
        <location
            file="src/main/res/drawable/cap_logo_light.xml"
            line="1"
            column="1"/>
    </issue>

    <issue
        id="UnusedResources"
        message="The resource `R.string.cap_a11_button_label` appears to be unused"
        errorLine1="  &lt;string name=&quot;cap_a11_button_label&quot;>Cash App Pay&lt;/string>"
        errorLine2="          ~~~~~~~~~~~~~~~~~~~~~~~~~~~">
        <location
            file="src/main/res/values/strings.xml"
            line="3"
            column="11"/>
    </issue>

    <issue
        id="UnusedResources"
        message="The resource `R.style.CAPButtonStyle` appears to be unused"
        errorLine1="  &lt;style name=&quot;CAPButtonStyle&quot; parent=&quot;android:Widget.ImageButton&quot;>"
        errorLine2="         ~~~~~~~~~~~~~~~~~~~~~">
        <location
            file="src/main/res/values/styles.xml"
            line="4"
            column="10"/>
    </issue>

    <issue
        id="UnusedResources"
        message="The resource `R.style.CAPButtonStyle_Light` appears to be unused"
        errorLine1="  &lt;style name=&quot;CAPButtonStyle.Light&quot;>"
        errorLine2="         ~~~~~~~~~~~~~~~~~~~~~~~~~~~">
        <location
            file="src/main/res/values/styles.xml"
            line="10"
            column="10"/>
    </issue>

    <issue
        id="UnusedResources"
        message="The resource `R.style.CAPButtonStyle_Dark` appears to be unused"
        errorLine1="  &lt;style name=&quot;CAPButtonStyle.Dark&quot;>"
        errorLine2="         ~~~~~~~~~~~~~~~~~~~~~~~~~~">
        <location
            file="src/main/res/values/styles.xml"
            line="15"
            column="10"/>
    </issue>

</issues>
